blocksmurfer/__init__.py
blocksmurfer/definitions.py
blocksmurfer-1.2.dist-info/METADATA
blocksmurfer-1.2.dist-info/WHEEL
blocksmurfer-1.2.dist-info/top_level.txt
blocksmurfer-1.2.dist-info/RECORD
